LICENSE
MANIFEST.in
README.txt
setup.py
django_sticky_messages.egg-info/PKG-INFO
django_sticky_messages.egg-info/SOURCES.txt
django_sticky_messages.egg-info/dependency_links.txt
django_sticky_messages.egg-info/top_level.txt
stickymessages/__init__.py
stickymessages/admin.py
stickymessages/context_processors.py
stickymessages/models.py
stickymessages/templates/stickymessages/display_latest_message.html