Metadata-Version: 1.0
Name: django-sticky-messages
Version: 0.1
Summary: A simple Django app to display "sticky" messages that expire after a given time period.
Home-page: https://github.com/rlepore/django-sticky-messages
Author: Ralph Lepore
Author-email: ralphlepore@gmail.com
License: MIT
Platform: UNKNOWN
Classifier: Environment :: Web Environment
Classifier: Framework :: Django
Classifier: Intended Audience :: Developers
Classifier: License :: OSI Approved :: BSD License
Classifier: Operating System :: OS Independent
Classifier: Programming Language :: Python
Classifier: Programming Language :: Python :: 2.6
Classifier: Programming Language :: Python :: 2.7
Classifier: Topic :: Internet :: WWW/HTTP
Classifier: Topic :: Internet :: WWW/HTTP :: Dynamic Content
